enverge_placeholder/__init__.py
enverge_placeholder/_version.py
enverge_placeholder-1.0.0.data/data/share/jupyter/labextensions/enverge_placeholder/build_log.json
enverge_placeholder-1.0.0.data/data/share/jupyter/labextensions/enverge_placeholder/package.json
enverge_placeholder-1.0.0.data/data/share/jupyter/labextensions/enverge_placeholder/schemas/enverge_placeholder/package.json.orig
enverge_placeholder-1.0.0.data/data/share/jupyter/labextensions/enverge_placeholder/schemas/enverge_placeholder/plugin.json
enverge_placeholder-1.0.0.data/data/share/jupyter/labextensions/enverge_placeholder/static/lib_index_js.2420ab94f907b97aea73.js
enverge_placeholder-1.0.0.data/data/share/jupyter/labextensions/enverge_placeholder/static/lib_index_js.2420ab94f907b97aea73.js.map
enverge_placeholder-1.0.0.data/data/share/jupyter/labextensions/enverge_placeholder/static/lib_index_js.2591f5cd2befb835c77c.js
enverge_placeholder-1.0.0.data/data/share/jupyter/labextensions/enverge_placeholder/static/lib_index_js.2591f5cd2befb835c77c.js.map
enverge_placeholder-1.0.0.data/data/share/jupyter/labextensions/enverge_placeholder/static/lib_index_js.2cc2e4ea7c9ab96cb411.js
enverge_placeholder-1.0.0.data/data/share/jupyter/labextensions/enverge_placeholder/static/lib_index_js.2cc2e4ea7c9ab96cb411.js.map
enverge_placeholder-1.0.0.data/data/share/jupyter/labextensions/enverge_placeholder/static/lib_index_js.652bff4a9af764c96acd.js
enverge_placeholder-1.0.0.data/data/share/jupyter/labextensions/enverge_placeholder/static/lib_index_js.652bff4a9af764c96acd.js.map
enverge_placeholder-1.0.0.data/data/share/jupyter/labextensions/enverge_placeholder/static/lib_index_js.88fd7d96fa90f697f254.js
enverge_placeholder-1.0.0.data/data/share/jupyter/labextensions/enverge_placeholder/static/lib_index_js.88fd7d96fa90f697f254.js.map
enverge_placeholder-1.0.0.data/data/share/jupyter/labextensions/enverge_placeholder/static/lib_index_js.8a719d68fa492c1f70db.js
enverge_placeholder-1.0.0.dist-info/METADATA
enverge_placeholder-1.0.0.dist-info/WHEEL
enverge_placeholder-1.0.0.dist-info/licenses/LICENSE
enverge_placeholder-1.0.0.dist-info/RECORD
