Metadata-Version: 2.4
Name: enverge_placeholder
Version: 1.0.0
Dynamic: Keywords
Summary: Enverge Placeholder
Project-URL: Homepage, https://github.com/Enverge-Labs/enverge_placeholder
Project-URL: Bug Tracker, https://github.com/Enverge-Labs/enverge_placeholder/issues
Project-URL: Repository, https://github.com/Enverge-Labs/enverge_placeholder.git
Author: jupyterlab-topbar contributors
License: BSD 3-Clause License
License-File: LICENSE
Classifier: Framework :: Jupyter
Classifier: Framework :: Jupyter :: JupyterLab
Classifier: Framework :: Jupyter :: JupyterLab :: 4
Classifier: Framework :: Jupyter :: JupyterLab :: Extensions
Classifier: Framework :: Jupyter :: JupyterLab :: Extensions :: Prebuilt
Classifier: License :: OSI Approved :: BSD License
Classifier: Programming Language :: Python
Classifier: Programming Language :: Python :: 3
Classifier: Programming Language :: Python :: 3.8
Classifier: Programming Language :: Python :: 3.9
Classifier: Programming Language :: Python :: 3.10
Classifier: Programming Language :: Python :: 3.11
Requires-Python: >=3.8
Requires-Dist: jupyterlab<5,>=4.0.0
